mongospawn/__init__.py
mongospawn/schema.py
mongospawn-0.5.10.dist-info/LICENSE
mongospawn-0.5.10.dist-info/METADATA
mongospawn-0.5.10.dist-info/WHEEL
mongospawn-0.5.10.dist-info/top_level.txt
mongospawn-0.5.10.dist-info/RECORD
