Metadata-Version: 2.1
Name: mongospawn
Version: 0.5.10
Summary: Spawn MongoDB resources from JSON Schema
Home-page: https://github.com/polyneme/mongospawn
Author: Donny Winston
Author-email: donny@polyneme.xyz
License: UNKNOWN
Platform: UNKNOWN
Classifier: Development Status :: 1 - Planning
Classifier: Development Status :: 2 - Pre-Alpha
Classifier: Programming Language :: Python :: 3
Classifier: License :: OSI Approved :: BSD License
Requires-Python: >=3.6
Requires-Dist: mongogrant
Requires-Dist: pymongo
Requires-Dist: python-dotenv
Provides-Extra: dev
Requires-Dist: black ; extra == 'dev'
Requires-Dist: invoke ; extra == 'dev'
Requires-Dist: pytest ; extra == 'dev'
Requires-Dist: setuptools-scm ; extra == 'dev'
Requires-Dist: twine ; extra == 'dev'
